plot_utils/__init__.py
plot_utils/colors_and_lines.py
plot_utils/helper.py
plot_utils/image.py
plot_utils/maps.py
plot_utils/misc.py
plot_utils/multiple_columns.py
plot_utils/one_column.py
plot_utils/time_series.py
plot_utils/two_columns.py
plot_utils/shapefiles/usa_counties/README.txt
plot_utils/shapefiles/usa_counties/cb_2016_us_county_500k.cpg
plot_utils/shapefiles/usa_counties/cb_2016_us_county_500k.dbf
plot_utils/shapefiles/usa_counties/cb_2016_us_county_500k.prj
plot_utils/shapefiles/usa_counties/cb_2016_us_county_500k.shp
plot_utils/shapefiles/usa_counties/cb_2016_us_county_500k.shp.ea.iso.xml
plot_utils/shapefiles/usa_counties/cb_2016_us_county_500k.shp.iso.xml
plot_utils/shapefiles/usa_counties/cb_2016_us_county_500k.shp.xml
plot_utils/shapefiles/usa_counties/cb_2016_us_county_500k.shx
plot_utils/shapefiles/usa_states/README.txt
plot_utils/shapefiles/usa_states/st99_d00.dbf
plot_utils/shapefiles/usa_states/st99_d00.shp
plot_utils/shapefiles/usa_states/st99_d00.shx
plot_utils-0.6.14.dist-info/LICENSE
plot_utils-0.6.14.dist-info/METADATA
plot_utils-0.6.14.dist-info/WHEEL
plot_utils-0.6.14.dist-info/top_level.txt
plot_utils-0.6.14.dist-info/RECORD
