Metadata-Version: 2.1
Name: plot_utils
Version: 0.6.14
Summary: A Python library for elegant data visualization
Home-page: https://github.com/jsh9/python-plot-utils
License: GPL v3.0
Classifier: License :: OSI Approved :: GNU General Public License v3 (GPLv3)
Classifier: Programming Language :: Python :: 2.7
Classifier: Programming Language :: Python :: 3
Classifier: Programming Language :: Python :: 3.4
Classifier: Programming Language :: Python :: 3.5
Classifier: Programming Language :: Python :: 3.6
Classifier: Programming Language :: Python :: 3.7
Classifier: Programming Language :: Python :: 3.8
Classifier: Programming Language :: Python :: 3.9
Classifier: Programming Language :: Python :: 3.10
Classifier: Programming Language :: Python :: 3.11
Requires-Python: !=3.0.*,!=3.1.*,!=3.2.*,!=3.3.*,>=2.7
License-File: LICENSE
